odoo/addons/report_qweb_decimal_place/README.rst
odoo/addons/report_qweb_decimal_place/__init__.py
odoo/addons/report_qweb_decimal_place/__manifest__.py
odoo/addons/report_qweb_decimal_place/i18n/es.po
odoo/addons/report_qweb_decimal_place/i18n/it.po
odoo/addons/report_qweb_decimal_place/i18n/report_qweb_decimal_place.pot
odoo/addons/report_qweb_decimal_place/models/__init__.py
odoo/addons/report_qweb_decimal_place/models/res_currency.py
odoo/addons/report_qweb_decimal_place/readme/CONFIGURE.rst
odoo/addons/report_qweb_decimal_place/readme/DESCRIPTION.rst
odoo/addons/report_qweb_decimal_place/reports/price_unit_value_format.xml
odoo/addons/report_qweb_decimal_place/static/description/icon.png
odoo/addons/report_qweb_decimal_place/static/description/index.html
odoo/addons/report_qweb_decimal_place/views/res_currency_views.xml
odoo_addon_report_qweb_decimal_place-16.0.1.0.0.8.dist-info/METADATA
odoo_addon_report_qweb_decimal_place-16.0.1.0.0.8.dist-info/WHEEL
odoo_addon_report_qweb_decimal_place-16.0.1.0.0.8.dist-info/top_level.txt
odoo_addon_report_qweb_decimal_place-16.0.1.0.0.8.dist-info/RECORD
