Metadata-Version: 2.1
Name: odoo-addon-report-qweb-decimal-place
Version: 16.0.1.0.0.8
Summary: Report Qweb Decimal Place
Home-page: https://github.com/OCA/reporting-engine
Author: Quartile Limited, Odoo Community Association (OCA)
Author-email: support@odoo-community.org
License: LGPL-3
Platform: UNKNOWN
Classifier: Programming Language :: Python
Classifier: Framework :: Odoo
Classifier: Framework :: Odoo :: 16.0
Classifier: License :: OSI Approved :: GNU Lesser General Public License v3 (LGPLv3)
Requires-Python: >=3.10
Requires-Dist: odoo <16.1dev,>=16.0a
